CHANGELOG
LICENSE
MANIFEST.in
README.md
setup.py
test.py
flaskey/__init__.py
flaskey/api.py
flaskey/base.py
flaskey/dummy.py
flaskey/utils.py
flaskey.egg-info/PKG-INFO
flaskey.egg-info/SOURCES.txt
flaskey.egg-info/dependency_links.txt
flaskey.egg-info/requires.txt
flaskey.egg-info/top_level.txt