Metadata-Version: 2.1
Name: flaskey
Version: 0.0.1
Summary: An extension of flask web framework of python that erase the complexity of constructing flask project blueprint, packages, and other annoying stuffs
Home-page: https://github.com/usmanmusa1920/flaskey
Author: Usman Musa
Author-email: usmanmusa1920@gmail.com
Keywords: flaskey
Classifier: Development Status :: 5 - Production/Stable
Classifier: Intended Audience :: Developers
Classifier: Natural Language :: English
Classifier: Operating System :: POSIX :: Linux
Classifier: License :: OSI Approved :: MIT License
Classifier: Programming Language :: Python
Classifier: Programming Language :: Python :: 3
License-File: LICENSE
